sietch/__init__.py
sietch/cli/__init__.py
sietch/cli/main.py
sietch/cli/parameters.py
sietch/directory/__init__.py
sietch/directory/directory.py
sietch/environment/__init__.py
sietch/environment/environment.py
sietch-0.2.0.dist-info/LICENSE
sietch-0.2.0.dist-info/METADATA
sietch-0.2.0.dist-info/WHEEL
sietch-0.2.0.dist-info/entry_points.txt
sietch-0.2.0.dist-info/top_level.txt
sietch-0.2.0.dist-info/RECORD
