Metadata-Version: 2.1
Name: sietch
Version: 0.2.0
Summary: Lightweight environment & cli tool
Home-page: https://github.com/GandalfsDad/sietch
Author: GandalfsDad
Classifier: License :: OSI Approved :: MIT License
Classifier: Programming Language :: Python :: 3
Classifier: Operating System :: OS Independent
Requires-Python: >=3.8
License-File: LICENSE
Requires-Dist: click
